{"component_button.md":"CfJQ0Tih","component_card.md":"5xty2kXS","component_checkbox.md":"8j9RhzS5","component_configprovide.md":"2KmaR9qG","component_container.md":"FBbyB8s2","component_icon.md":"DR197L5-","component_input.md":"BWM_diiz","component_layout.md":"XwKI0RF5","component_link.md":"C_3bAyYC","component_scrollbar.md":"C4zyvBvX","component_space.md":"Lsvwxx2H","component_start.md":"BhEuZy37","component_tabel.md":"Bn85c-TE","component_text.md":"DKRksE6W","guide_getstart.md":"YxzYcqLX","guide_installtion.md":"C4lTA5s_","index.md":"CoBubn-6"}
